{
  "name": "Phillip Keller",
  "age": 62,
  "address": {
    "street": "Leta Plaza",
    "city": "Cannovati",
    "state": "AZ",
    "zip": "63921"
  },
  "contact": {
    "phone": "(432) 884-5901",
    "servicePhone": "800648351"
  },
  "birthday": "1976-05-18T19:29:00.151Z",
  "ip": "16.13.15.135",
  "foo": "bar",
  "profile": {
    "about": "Vo dajfeftuw bi zidken gib zufuc oje gelguc bos icaicev uwitu bi pu obidej dam zugivkec ucawulum urmos. Avha ki dijidwu do zadignu ritmuptep zopume zot evjidete dackejmis tegabu geg gug ci uco edfocot le ja. Nechut natijvef faw uh fiwiz dojzoji duwpod dajbow ubieli ci bassaoza fitus fa is.",
    "bio": "Lobwe sip toifi geutuki kuhuh nuofolo igbedlil susmezij ozacih mi fuvaha vip kari. Ru hedinzo ne iwfiju dicibfuk wate bare oteira gehgoccin vunse co mief polci gori. Jomriri to ha kiecaas woz iluriid bek di kivvug ek luzo cigape fadum wepniob commefkes pogoem bu. Waud giafjis wimuha lensite sanba mufa utca fatga ugacuum opiejazut zuw eb uh codusem. Tu kuw ni mosmep lilocja subatol galunvem ovipicin git kuhesowup leg vajco bocba."
  },
  "apiKey": "f86e128a5647b08a2c3332eec4c58bf388898acbc4b50defafd63060df581855",
  "currency": {
    "code": "TRY",
    "name": "Turkey Lira"
  }
}