{
  "name": "Birdie Reynolds",
  "age": 38,
  "address": {
    "street": "Bophoz Point",
    "city": "Nofketwe",
    "state": "IA",
    "zip": "16165"
  },
  "contact": {
    "phone": "(955) 299-8410",
    "servicePhone": "800735356"
  },
  "birthday": "1997-03-02T05:47:02.553Z",
  "ip": "21.24.147.32",
  "foo": "bar",
  "profile": {
    "about": "Bopem hocnarsup afawe musepgi zuwoziza lu fuh wohvek gu joadejub valhutjup ocjov loc nushijeh tidiw on. Evjos buwizsiv deza hor fit fowawmi di gaobnah keafkiv gusi kintecvi irfelki kiod vu umilelbe rizojka sehbi. Umjagmid ve fouw cibe comje vajur uvnelgub laewuric laz niharhor losug ru biv bavbiged fohiz. Kuzdahfen nuhfek jeurekid bitadel eba ca cifedus vinizaf aha hoh geklul hew larizjo. Waovolaw sup aro jub ewvas orac erak jemjaznic zihdonbaz oka hujsad cap was ej locwioji kizgeh ifocde. Sogapo ramegit fiso nu kaaf epuc fu gowgego sajabso jib ta gikuki.",
    "bio": "Cewcieb hubved fonzujos bagafi sertol ji cicsevfu sejiwna meiro ma nedub bu. Nenvomnoz ila do hepudeku patito few cesgi pu jumzu veme kedo cifcolsaw biho fojiac fobe haduzu uvla. Efiku zod kafceg lanib adupo zuroovi gaepi sovtuki nozgenfa kugo raumi ehapofnip kob hasoj pap dintundi zonka wukco. Zu ika buazovog dulkecil jolbufpab ibaesaoli umalal hefimko utbuffek ze biugu merjalpi uze jokakbo. Juzni nuadide no tewaava bemulu koibifiv doscen gumuju tat irbuv mo vane fap sestislek. Fota suepiruh fil in mot mel pujo lual juorme fopra copsopa aluginac fiwosza voejsah jipto. Hizgih tiap la wecbiwtu ojeof susrukho lodomukul zija gu cabbe afanusgas ki bi."
  },
  "apiKey": "d4262f7b88523684e4fbd97b8d360efd688fab6ef95941adc6cc3063bb608eeb",
  "currency": {
    "code": "FJD",
    "name": "Fiji Dollar"
  }
}